MANIFEST.in
README.rst
setup.py
mygtk/Calendar.py
mygtk/__init__.py
mygtk.egg-info/PKG-INFO
mygtk.egg-info/SOURCES.txt
mygtk.egg-info/dependency_links.txt
mygtk.egg-info/requires.txt
mygtk.egg-info/top_level.txt