Metadata-Version: 1.0
Name: mygtk
Version: 0.0.4
Summary: my personal gtk widget extensions
Home-page: https://oxidworks.de/
Author: oxidworks
Author-email: apps@oxidworks.de
License: UNKNOWN
Platform: UNKNOWN
